zmq_anyio/__init__.py
zmq_anyio/_socket.py
zmq_anyio/py.typed
zmq_anyio-0.3.13.dist-info/WHEEL
zmq_anyio-0.3.13.dist-info/METADATA
zmq_anyio-0.3.13.dist-info/RECORD
