Metadata-Version: 2.3
Name: zmq-anyio
Version: 0.3.13
Summary: Asynchronous API for ZMQ using AnyIO
Author: David Brochart
Author-email: David Brochart <david.brochart@gmail.com>
License: BSD 3-Clause License
Classifier: Development Status :: 4 - Beta
Classifier: Intended Audience :: Developers
Classifier: License :: OSI Approved :: BSD License
Classifier: Typing :: Typed
Classifier: Topic :: System :: Networking
Classifier: Programming Language :: Python
Classifier: Programming Language :: Python :: 3
Classifier: Programming Language :: Python :: 3.10
Classifier: Programming Language :: Python :: 3.11
Classifier: Programming Language :: Python :: 3.12
Classifier: Programming Language :: Python :: 3.13
Classifier: Programming Language :: Python :: 3.14
Classifier: Programming Language :: Python :: Implementation :: CPython
Classifier: Programming Language :: Python :: Implementation :: PyPy
Requires-Dist: anyio>=4.10.0,<5.0.0
Requires-Dist: anyioutils>=0.7.1,<0.8.0
Requires-Dist: pyzmq>=26.0.0,<28.0.0
Requires-Python: >=3.10
Project-URL: Issues, https://github.com/QuantStack/zmq-anyio/issues
Project-URL: Source, https://github.com/QuantStack/zmq-anyio
